[
  {
    "id": "ppf-1768041585581-rc8q3coen",
    "memberId": "MRNOI00540970000010276",
    "memberName": "RAJENDRA PRASAD",
    "establishmentId": "MRNOI0054097000/TO",
    "establishmentName": "THE",
    "depositEmployeeShare": 1234920,
    "depositEmployerShare": 1042624,
    "withdrawEmployeeShare": 0,
    "withdrawEmployerShare": 0,
    "pensionContribution": 108709,
    "grandTotal": 2386253,
    "extractedFrom": "PDFView.pdf",
    "extractedAt": "2026-01-10T10:39:45.581Z",
    "rawData": {
      "memberId": "MRNOI00540970000010276",
      "memberName": "RAJENDRA PRASAD",
      "establishmentId": "MRNOI0054097000/TO",
      "establishmentName": "THE",
      "depositEmployeeShare": 1234920,
      "depositEmployerShare": 1042624,
      "withdrawEmployeeShare": 0,
      "withdrawEmployerShare": 0,
      "pensionContribution": 108709,
      "grandTotal": 2386253
    }
  },
  {
    "id": "ppf-1768041586448-3nfkfn6bn",
    "memberId": "MRNOI00487490000000187",
    "memberName": "RAJENDRA PRASAD",
    "establishmentId": "MRNOI0048749000/",
    "establishmentName": "INTELLIGRAPE SOFTWARE",
    "depositEmployeeShare": 385038,
    "depositEmployerShare": 251693,
    "withdrawEmployeeShare": 0,
    "withdrawEmployerShare": 0,
    "pensionContribution": 42319,
    "grandTotal": 679050,
    "extractedFrom": "PDFView 2.pdf",
    "extractedAt": "2026-01-10T10:39:46.448Z",
    "rawData": {
      "memberId": "MRNOI00487490000000187",
      "memberName": "RAJENDRA PRASAD",
      "establishmentId": "MRNOI0048749000/",
      "establishmentName": "INTELLIGRAPE SOFTWARE",
      "depositEmployeeShare": 385038,
      "depositEmployerShare": 251693,
      "withdrawEmployeeShare": 0,
      "withdrawEmployerShare": 0,
      "pensionContribution": 42319,
      "grandTotal": 679050
    }
  }
]